nonebot_plugin_xiuxian_GCDI/__init__.py
nonebot_plugin_xiuxian_GCDI/cd_manager.py
nonebot_plugin_xiuxian_GCDI/command.py
nonebot_plugin_xiuxian_GCDI/data_source.py
nonebot_plugin_xiuxian_GCDI/help.py
nonebot_plugin_xiuxian_GCDI/item_json.py
nonebot_plugin_xiuxian_GCDI/player_fight.py
nonebot_plugin_xiuxian_GCDI/read_buff.py
nonebot_plugin_xiuxian_GCDI/utils.py
nonebot_plugin_xiuxian_GCDI/xiuxian2_handle.py
nonebot_plugin_xiuxian_GCDI/xiuxian_config.py
nonebot_plugin_xiuxian_GCDI/xiuxian_opertion.py
nonebot_plugin_xiuxian_GCDI/xiuxian_back/__init__.py
nonebot_plugin_xiuxian_GCDI/xiuxian_back/back_util.py
nonebot_plugin_xiuxian_GCDI/xiuxian_back/backconfig.py
nonebot_plugin_xiuxian_GCDI/xiuxian_bank/__init__.py
nonebot_plugin_xiuxian_GCDI/xiuxian_bank/bankconfig.py
nonebot_plugin_xiuxian_GCDI/xiuxian_boss/__init__.py
nonebot_plugin_xiuxian_GCDI/xiuxian_boss/bossconfig.py
nonebot_plugin_xiuxian_GCDI/xiuxian_boss/makeboss.py
nonebot_plugin_xiuxian_GCDI/xiuxian_buff/__init__.py
nonebot_plugin_xiuxian_GCDI/xiuxian_info/__init__.py
nonebot_plugin_xiuxian_GCDI/xiuxian_info/download.py
nonebot_plugin_xiuxian_GCDI/xiuxian_info/draw_user_info.py
nonebot_plugin_xiuxian_GCDI/xiuxian_info/font.ttf
nonebot_plugin_xiuxian_GCDI/xiuxian_info/infoconfig.py
nonebot_plugin_xiuxian_GCDI/xiuxian_info/send_image_tool.py
nonebot_plugin_xiuxian_GCDI/xiuxian_info/texture2d/back.png
nonebot_plugin_xiuxian_GCDI/xiuxian_info/texture2d/line2.png
nonebot_plugin_xiuxian_GCDI/xiuxian_info/texture2d/line3.png
nonebot_plugin_xiuxian_GCDI/xiuxian_info/texture2d/line4.png
nonebot_plugin_xiuxian_GCDI/xiuxian_info/texture2d/user_state.png
nonebot_plugin_xiuxian_GCDI/xiuxian_mixelixir/__init__.py
nonebot_plugin_xiuxian_GCDI/xiuxian_mixelixir/mix_elixir_config.py
nonebot_plugin_xiuxian_GCDI/xiuxian_mixelixir/mixelixirutil.py
nonebot_plugin_xiuxian_GCDI/xiuxian_pray/__init__.py
nonebot_plugin_xiuxian_GCDI/xiuxian_rift/__init__.py
nonebot_plugin_xiuxian_GCDI/xiuxian_rift/jsondata.py
nonebot_plugin_xiuxian_GCDI-1.0.3.dist-info/LICENSE.txt
nonebot_plugin_xiuxian_GCDI-1.0.3.dist-info/METADATA
nonebot_plugin_xiuxian_GCDI-1.0.3.dist-info/WHEEL
nonebot_plugin_xiuxian_GCDI-1.0.3.dist-info/top_level.txt
nonebot_plugin_xiuxian_GCDI-1.0.3.dist-info/RECORD
