Metadata-Version: 2.1
Name: nonebot-plugin-xiuxian-GCDI
Version: 1.0.3
Summary: 修仙插件，QQ群与QQ频道均可使用，并且数据互通
Home-page: https://github.com/QingMuCat/nonebot_plugin_xiuxian_GCDI
Author: QingmuCat
Author-email: 1242550160@qq.com
Keywords: pip,nonebot2,文游,修仙
Platform: any
Classifier: Programming Language :: Python :: 3
Classifier: License :: OSI Approved :: GNU General Public License v3 (GPLv3)
Classifier: Natural Language :: Chinese (Simplified)
License-File: LICENSE.txt
Requires-Dist: httpx
Requires-Dist: wcwidth
Requires-Dist: nonebot-adapter-onebot
Requires-Dist: nonebot-plugin-apscheduler
Requires-Dist: Pillow
Requires-Dist: nonebot-plugin-guild-patch
Requires-Dist: snoop
